channels_endpoints/__init__.py
channels_endpoints/apps.py
channels_endpoints/auth.py
channels_endpoints/client.py
channels_endpoints/exceptions.py
channels_endpoints/main.py
channels_endpoints/utils.py
channels_endpoints-1.0.3.dist-info/LICENSE
channels_endpoints-1.0.3.dist-info/METADATA
channels_endpoints-1.0.3.dist-info/WHEEL
channels_endpoints-1.0.3.dist-info/top_level.txt
channels_endpoints-1.0.3.dist-info/RECORD
