Metadata-Version: 2.1
Name: channels-endpoints
Version: 1.0.3
Summary: Django channels endpoints
Home-page: https://github.com/avigmati/channels_endpoints
Author: Dmitry Novikov
Author-email: avigmati@gmail.com
License: UNKNOWN
Project-URL: Bug Tracker, https://github.com/avigmati/channels_endpoints/issues
Platform: UNKNOWN
Classifier: Programming Language :: Python :: 3
Classifier: License :: OSI Approved :: MIT License
Classifier: Operating System :: OS Independent
Requires-Python: >=3.9
License-File: LICENSE
Requires-Dist: aiohttp (>=3.7.4)
